twi_nlp/__init__.py
twi_nlp/twi_nlp.py
twi_nlp/utils.py
twi_nlp-1.0.0.dist-info/METADATA
twi_nlp-1.0.0.dist-info/WHEEL
twi_nlp-1.0.0.dist-info/top_level.txt
twi_nlp-1.0.0.dist-info/RECORD
