Metadata-Version: 2.4
Name: twi_nlp
Version: 1.0.0
Summary: A Twi NLP package for translation, POS tagging, tokenization, stemming, and lemmatization.
Home-page: https://github.com/birdcoreone/TNLP-python
Author: Teddy Boamah (Birdcore)
Author-email: saintt442@gmail.com
Classifier: Programming Language :: Python :: 3
Classifier: License :: OSI Approved :: Apache Software License
Classifier: Operating System :: OS Independent
Requires-Python: >=3.6
Requires-Dist: pandas
Requires-Dist: nltk
Requires-Dist: regex
Requires-Dist: chardet
Requires-Dist: urllib3
Dynamic: author
Dynamic: author-email
Dynamic: classifier
Dynamic: description
Dynamic: description-content-type
Dynamic: home-page
Dynamic: requires-dist
Dynamic: requires-python
Dynamic: summary
